django_sql_log_middleware/__init__.py
django_sql_log_middleware/django_sql_log_middleware.py
django_sql_log_middleware-0.1.8.dist-info/LICENSE
django_sql_log_middleware-0.1.8.dist-info/METADATA
django_sql_log_middleware-0.1.8.dist-info/WHEEL
django_sql_log_middleware-0.1.8.dist-info/top_level.txt
django_sql_log_middleware-0.1.8.dist-info/RECORD
