Metadata-Version: 2.1
Name: django-sql-log-middleware
Version: 0.1.8
Summary: Write Django's SQL statements to a JSONL log file
Home-page: https://github.com/JonnoFTW/django-sql-log-middleware
Author: JonnoFTW
Author-email: jonmac1@gmail.com
License: MIT
Platform: UNKNOWN
Classifier: Intended Audience :: Developers
Classifier: Natural Language :: English
Classifier: License :: OSI Approved :: MIT License
Classifier: Operating System :: OS Independent
Classifier: Programming Language :: Python
Classifier: Programming Language :: Python :: 3
Classifier: Topic :: Software Development :: Libraries :: Python Modules
Classifier: Framework :: Django
License-File: LICENSE
Requires-Dist: Django
